gpp_decrypt/__init__.py
gpp_decrypt/cli.py
gpp_decrypt/core.py
gpp_decrypt-2.0.0.dist-info/licenses/LICENSE
gpp_decrypt-2.0.0.dist-info/METADATA
gpp_decrypt-2.0.0.dist-info/WHEEL
gpp_decrypt-2.0.0.dist-info/entry_points.txt
gpp_decrypt-2.0.0.dist-info/top_level.txt
gpp_decrypt-2.0.0.dist-info/RECORD
