Metadata-Version: 2.4
Name: gpp-decrypt
Version: 2.0.0
Summary: A tool to decrypt Group Policy Preferences (GPP) cpassword attributes
Author: Kristof Toth
Author-email: Kristof Toth <t0thkr1s@icloud.com>
Project-URL: Homepage, https://github.com/t0thkr1s/gpp-decrypt
Project-URL: Bug Tracker, https://github.com/t0thkr1s/gpp-decrypt/issues
Project-URL: Source, https://github.com/t0thkr1s/gpp-decrypt
Keywords: security,windows,active-directory,gpp,group-policy,pentesting,red-team
Classifier: Development Status :: 5 - Production/Stable
Classifier: Intended Audience :: Information Technology
Classifier: Intended Audience :: System Administrators
Classifier: License :: OSI Approved :: GNU General Public License v3 (GPLv3)
Classifier: Operating System :: OS Independent
Classifier: Programming Language :: Python :: 3
Classifier: Programming Language :: Python :: 3.8
Classifier: Programming Language :: Python :: 3.9
Classifier: Programming Language :: Python :: 3.10
Classifier: Programming Language :: Python :: 3.11
Classifier: Programming Language :: Python :: 3.12
Classifier: Topic :: Security
Classifier: Topic :: System :: Systems Administration
Requires-Python: >=3.8
License-File: LICENSE
Requires-Dist: pycryptodome>=3.15.0
Requires-Dist: colorama>=0.4.4
Dynamic: author
Dynamic: license-file
